[
  {
    "sinav": "2024 - YDS/2",
    "islemtipi": "Cevap Kağıdı Görüntüleme",
    "sinavtarihi": "03.11.2024",
    "islemtarihi": "22.11.2024 10.45",
    "durum": "Görüntüleme Başladı"
  },
  {
    "sinav": "2024 - YDUS 1.Dönem Ek Tercih (Grup 2)",
    "islemtipi": "Tercih",
    "sinavtarihi": "-",
    "islemtarihi": "19.11.2024 10.00-25.11.2024 23.59",
    "durum": "Devam Ediyor"
  },
  {
    "sinav": "2024 - ALES/3",
    "islemtipi": "Temel Soru Kitapçığı Görüntüleme",
    "sinavtarihi": "17.11.2024",
    "islemtarihi": "17.11.2024 13.20-27.11.2024 23.59",
    "durum": "Devam Ediyor"
  },
  {
    "sinav": "2024 - BKUBTS",
    "islemtipi": "Sınava Giriş Belgesi Dökümü",
    "sinavtarihi": "24.11.2024",
    "islemtarihi": "14.11.2024 11.00-24.11.2024 23.59",
    "durum": "Bitti"
  }
]